gotstopwords/__init__.py
gotstopwords/gotstopwords.py
gotstopwords/iso6391codes.py
gotstopwords/data/nltk/arabic
gotstopwords/data/nltk/azerbaijani
gotstopwords/data/nltk/basque
gotstopwords/data/nltk/bengali
gotstopwords/data/nltk/catalan
gotstopwords/data/nltk/chinese
gotstopwords/data/nltk/danish
gotstopwords/data/nltk/dutch
gotstopwords/data/nltk/english
gotstopwords/data/nltk/finnish
gotstopwords/data/nltk/french
gotstopwords/data/nltk/german
gotstopwords/data/nltk/greek
gotstopwords/data/nltk/hebrew
gotstopwords/data/nltk/hinglish
gotstopwords/data/nltk/hungarian
gotstopwords/data/nltk/indonesian
gotstopwords/data/nltk/italian
gotstopwords/data/nltk/kazakh
gotstopwords/data/nltk/nepali
gotstopwords/data/nltk/norwegian
gotstopwords/data/nltk/portuguese
gotstopwords/data/nltk/romanian
gotstopwords/data/nltk/russian
gotstopwords/data/nltk/slovene
gotstopwords/data/nltk/spanish
gotstopwords/data/nltk/swedish
gotstopwords/data/nltk/tajik
gotstopwords/data/nltk/turkish
gotstopwords/data/other/arabic
gotstopwords/data/other/armenian
gotstopwords/data/other/bulgarian
gotstopwords/data/other/chinese
gotstopwords/data/other/danish
gotstopwords/data/other/dutch
gotstopwords/data/other/english
gotstopwords/data/other/finnish
gotstopwords/data/other/french
gotstopwords/data/other/german
gotstopwords/data/other/greek
gotstopwords/data/other/hindi1
gotstopwords/data/other/hindi2
gotstopwords/data/other/indonesian
gotstopwords/data/other/italian
gotstopwords/data/other/japanese
gotstopwords/data/other/latvian
gotstopwords/data/other/norwegian
gotstopwords/data/other/persian
gotstopwords/data/other/polish1
gotstopwords/data/other/polish2
gotstopwords/data/other/portuguese
gotstopwords/data/other/romanian
gotstopwords/data/other/russian
gotstopwords/data/other/spanish
gotstopwords/data/other/swedish
gotstopwords/data/other/turkish
gotstopwords-1.0.7.dist-info/METADATA
gotstopwords-1.0.7.dist-info/WHEEL
gotstopwords-1.0.7.dist-info/licenses/LICENSE
gotstopwords-1.0.7.dist-info/RECORD
