Metadata-Version: 2.1
Name: gotstopwords
Version: 1.0.7
Summary: Package that simplifies the use of stop words lists with Python NLP projects in 36 languages.
Project-URL: Homepage, https://github.com/pictureinthenoise/gotstopwords
Project-URL: Bug Tracker, https://github.com/pictureinthenoise/gotstopwords/issues
Author-email: pictureinthenoise <pictureinthenoise@protonmail.com>
License-File: LICENSE
Classifier: License :: OSI Approved :: MIT License
Classifier: Operating System :: OS Independent
Classifier: Programming Language :: Python :: 3
Requires-Python: >=3.7
